infusion/Context.py
infusion/__init__.py
infusion/__version__.py
infusion/exceptions/ContextKeyMissing.py
infusion/exceptions/__init__.py
infusion-0.1.4.dist-info/METADATA
infusion-0.1.4.dist-info/WHEEL
infusion-0.1.4.dist-info/top_level.txt
infusion-0.1.4.dist-info/RECORD
