Metadata-Version: 2.1
Name: infusion
Version: 0.1.4
Summary: Simplistic framework for structuring data science and machine learning pipelines.
Home-page: https://github.com/sitnarf/infusion
Author: František Sabovčik
Author-email: sitnarf@gmail.com
License: MIT
Platform: UNKNOWN
Classifier: Development Status :: 2 - Pre-Alpha
Classifier: License :: OSI Approved :: MIT License
Classifier: Programming Language :: Python
Classifier: Programming Language :: Python :: 3
Classifier: Programming Language :: Python :: 3.6
Classifier: Programming Language :: Python :: Implementation :: CPython
Classifier: Operating System :: OS Independent
Classifier: Topic :: Software Development :: Libraries :: Python Modules
Requires-Python: >=3.5.0
